andeggs/__init__.py
andeggs/client.py
and_eggs-0.0.7.dist-info/LICENSE
and_eggs-0.0.7.dist-info/METADATA
and_eggs-0.0.7.dist-info/WHEEL
and_eggs-0.0.7.dist-info/top_level.txt
and_eggs-0.0.7.dist-info/RECORD
