Metadata-Version: 2.1
Name: and-eggs
Version: 0.0.7
Summary: GMail Bot API
Home-page: UNKNOWN
Author: LemonChad
Author-email: jaolsm6296@gmail.com
License: UNKNOWN
Platform: UNKNOWN
Classifier: Programming Language :: Python :: 3
Classifier: License :: OSI Approved :: MIT License
Classifier: Operating System :: OS Independent
Requires-Python: >=3.6
